README.md
nice_parametrize.py
setup.cfg
setup.py
pytest_nice_parametrize.egg-info/PKG-INFO
pytest_nice_parametrize.egg-info/SOURCES.txt
pytest_nice_parametrize.egg-info/dependency_links.txt
pytest_nice_parametrize.egg-info/requires.txt
pytest_nice_parametrize.egg-info/top_level.txt