Metadata-Version: 2.1
Name: pytest-nice-parametrize
Version: 1.0.1
Summary: A small snippet for nicer PyTest's Parametrize
Home-page: UNKNOWN
Author: Yam Tirosh
Author-email: yam.tirosh@gmail.com
License: MIT
Download-URL: https://github.com/yamti1/pytest-nice-parametrize/archive/refs/tags/1.0.0.tar.gz
Keywords: pytest parametrize ids
Platform: UNKNOWN
Classifier: Development Status :: 5 - Production/Stable
Classifier: Intended Audience :: Developers
Classifier: License :: OSI Approved :: MIT License
Classifier: Programming Language :: Python :: 3
Classifier: Programming Language :: Python :: 2.7
